{"summary_total":{"quarterly":{"current":{"label":"Q1 FY 2027","value":58.2687,"qoq":-0.1273,"yoy":0.1385},"previous":{"label":"Q4 FY 2026","value":66.7685},"prev2":{"label":"Q1 FY 2026","value":51.1821}},"monthly":{"current":{"label":"FY 2027 June","value":54.075,"mom":-0.1133,"mo6m":-0.1345},"previous":{"label":"FY 2027 May","value":60.9853},"avg_6m":{"label":"Avg Of Last 6 Months","value":62.4794}},"weekly":{"last5":{"label":"Last 5 Trading Days","value":49.9701,"wow":-0.0738,"wo10w":-0.1283},"prev5":{"label":"Previous 5 Trading Days","value":53.9512},"last45":{"label":"Last 45 Trading Days","value":57.3271}},"day_of_week":{"Monday":{"latest":61.131,"do3d":0.0137,"do10d":-0.0694,"avg_3d":60.3067,"avg_10d":65.6902},"Tuesday":{"latest":56.5262,"do3d":-0.1708,"do10d":-0.2213,"avg_3d":68.1703,"avg_10d":72.5944},"Wednesday":{"latest":35.9358,"do3d":-0.1797,"do10d":-0.2147,"avg_3d":43.8093,"avg_10d":45.7587},"Thursday":{"latest":34.4913,"do3d":-0.0765,"do10d":-0.2183,"avg_3d":37.3469,"avg_10d":44.1247},"Friday":{"latest":61.7663,"do3d":-0.0632,"do10d":-0.0491,"avg_3d":65.9301,"avg_10d":64.9569}},"previous_week":{"Friday":66.3861,"Monday":58.1994,"Tuesday":66.3906,"Wednesday":41.4417,"Thursday":37.3384},"fy":{"current":58.2687,"previous":52.1856,"yoy":0.1166}},"seg_options":{"quarterly":{"current":{"label":"Q1 FY 2027","value":45.4172,"qoq":-0.1512,"yoy":0.1678},"previous":{"label":"Q4 FY 2026","value":53.5083},"prev2":{"label":"Q1 FY 2026","value":38.8928}},"monthly":{"current":{"label":"FY 2027 June","value":43.4529,"mom":-0.0777,"mo6m":-0.1225},"previous":{"label":"FY 2027 May","value":47.1142},"avg_6m":{"label":"Avg Of Last 6 Months","value":49.5173}},"weekly":{"last5":{"label":"Last 5 Trading Days","value":39.1414,"wow":-0.112,"wo10w":-0.1149},"prev5":{"label":"Previous 5 Trading Days","value":44.0784},"last45":{"label":"Last 45 Trading Days","value":44.2228}},"day_of_week":{"Monday":{"latest":49.2722,"do3d":-0.0079,"do10d":-0.067,"avg_3d":49.6628,"avg_10d":52.8114},"Tuesday":{"latest":46.8772,"do3d":-0.1854,"do10d":-0.2256,"avg_3d":57.5479,"avg_10d":60.5318},"Wednesday":{"latest":25.056,"do3d":-0.2384,"do10d":-0.2591,"avg_3d":32.8973,"avg_10d":33.8173},"Thursday":{"latest":23.446,"do3d":-0.1367,"do10d":-0.2425,"avg_3d":27.16,"avg_10d":30.9529},"Friday":{"latest":51.0556,"do3d":-0.002,"do10d":0.0352,"avg_3d":51.1583,"avg_10d":49.3181}},"previous_week":{"Friday":55.4781,"Monday":49.0808,"Tuesday":56.2443,"Wednesday":31.4301,"Thursday":28.1588},"fy":{"current":45.4172,"previous":40.3978,"yoy":0.1242}},"seg_futures":{"quarterly":{"current":{"label":"Q1 FY 2027","value":4.823,"qoq":-0.2164,"yoy":-0.1724},"previous":{"label":"Q4 FY 2026","value":6.155},"prev2":{"label":"Q1 FY 2026","value":5.8277}},"monthly":{"current":{"label":"FY 2027 June","value":3.0779,"mom":-0.4361,"mo6m":-0.4312},"previous":{"label":"FY 2027 May","value":5.4579},"avg_6m":{"label":"Avg Of Last 6 Months","value":5.4112}},"weekly":{"last5":{"label":"Last 5 Trading Days","value":3.1739,"wow":0.1248,"wo10w":-0.3666},"prev5":{"label":"Previous 5 Trading Days","value":2.8218},"last45":{"label":"Last 45 Trading Days","value":5.0107}},"day_of_week":{"Monday":{"latest":3.6234,"do3d":0.1655,"do10d":-0.3049,"avg_3d":3.109,"avg_10d":5.2125},"Tuesday":{"latest":2.5436,"do3d":-0.1455,"do10d":-0.4184,"avg_3d":2.9767,"avg_10d":4.3733},"Wednesday":{"latest":2.9577,"do3d":-0.0817,"do10d":-0.245,"avg_3d":3.221,"avg_10d":3.9173},"Thursday":{"latest":3.0933,"do3d":0.1229,"do10d":-0.3946,"avg_3d":2.7548,"avg_10d":5.1093},"Friday":{"latest":3.6517,"do3d":-0.1255,"do10d":-0.4569,"avg_3d":4.1756,"avg_10d":6.7236}},"previous_week":{"Friday":3.2531,"Monday":2.6302,"Tuesday":2.8281,"Wednesday":2.9006,"Thursday":2.497},"fy":{"current":4.823,"previous":5.5167,"yoy":-0.1257}},"seg_cash":{"quarterly":{"current":{"label":"Q1 FY 2027","value":8.0285,"qoq":0.13,"yoy":0.2425},"previous":{"label":"Q4 FY 2026","value":7.1052},"prev2":{"label":"Q1 FY 2026","value":6.4616}},"monthly":{"current":{"label":"FY 2027 June","value":7.5443,"mom":-0.1033,"mo6m":-0.0009},"previous":{"label":"FY 2027 May","value":8.4132},"avg_6m":{"label":"Avg Of Last 6 Months","value":7.551}},"weekly":{"last5":{"label":"Last 5 Trading Days","value":7.6548,"wow":0.0856,"wo10w":-0.0542},"prev5":{"label":"Previous 5 Trading Days","value":7.051},"last45":{"label":"Last 45 Trading Days","value":8.0937}},"day_of_week":{"Monday":{"latest":8.2354,"do3d":0.093,"do10d":0.0742,"avg_3d":7.5348,"avg_10d":7.6663},"Tuesday":{"latest":7.1054,"do3d":-0.0707,"do10d":-0.0759,"avg_3d":7.6457,"avg_10d":7.6894},"Wednesday":{"latest":7.9221,"do3d":0.03,"do10d":-0.0127,"avg_3d":7.691,"avg_10d":8.0242},"Thursday":{"latest":7.952,"do3d":0.07,"do10d":-0.0137,"avg_3d":7.4321,"avg_10d":8.0625},"Friday":{"latest":7.059,"do3d":-0.3338,"do10d":-0.2082,"avg_3d":10.5962,"avg_10d":8.9153}},"previous_week":{"Friday":7.6549,"Monday":6.4883,"Tuesday":7.3182,"Wednesday":7.111,"Thursday":6.6826},"fy":{"current":8.0285,"previous":6.271,"yoy":0.2803}},"pnl_predictor":{"daily_avg_rev":58.2687,"q4_fy2026_trading_days_so_far":53,"q4_fy2025_total_trading_days":62,"transaction_rev_extrapolated":3612.66,"other_income_ratio":0.4961,"total_revenue_predicted":5404.85,"pat_predicted":3064.55},"pnl_predicted_quarters":{"Q1 FY 2027":{"transaction_rev":3612.66,"total_revenue":5404.85,"total_expense":1597.83,"ebitda":3807.02,"ebitda_margin":0.7044,"pat":2952.87,"pat_margin":0.5463,"eps":11.93},"Q2 FY 2027":{"transaction_rev":3573.43,"total_revenue":5346.22,"total_expense":1580.5,"ebitda":3765.72,"ebitda_margin":0.7044,"pat":2920.84,"pat_margin":0.5463,"eps":11.8}}}