{
  "updated_at": "2026-07-15T05:19:32",
  "sensex": {
    "last": 77590.64,
    "change": 535.7,
    "pct_change": 0.7,
    "prev_close": 77054.94,
    "open": 77192.76,
    "high": 77641.86,
    "low": 77072.53,
    "datetime": "15 Jul 26 | 10:48",
    "status": "Open"
  },
  "market_stat": {
    "market_cap_cr": 48291932.79,
    "market_cap_usd_t": 5.02,
    "turnover_cr": 3762.49,
    "listed_companies": 5163,
    "advances": 2543,
    "declines": 1148,
    "unchanged": 222
  },
  "revenue": {
    "trade_date": "15/07/26",
    "equity_turnover": 3799.63,
    "derivatives_notional": 5140369.35,
    "options_premium": 9943.95,
    "cash_revenue": 0.285,
    "options_revenue": 6.4636,
    "futures_revenue": 0.0,
    "total_revenue": 6.7485,
    "has_data": true,
    "source": "live"
  },
  "stock_price": {
    "last_price": 3784.7,
    "previous_close": 3799.5,
    "open": 3800.0,
    "day_high": 3830.4,
    "day_low": 3751.0,
    "pct_change": -0.39
  }
}