{
  "updated_at": "2026-04-24T09:12:09",
  "sensex": {
    "last": 76697.67,
    "change": -966.33,
    "pct_change": -1.24,
    "prev_close": 77664.0,
    "open": 77483.8,
    "high": 77710.82,
    "low": 76403.87,
    "datetime": "24 Apr 26 | 14:42",
    "status": "Open"
  },
  "market_stat": {
    "market_cap_cr": 46185714.83,
    "market_cap_usd_t": 4.9,
    "turnover_cr": 7845.7,
    "listed_companies": 5116,
    "advances": 1193,
    "declines": 2961,
    "unchanged": 161
  },
  "revenue": {
    "trade_date": "24/04/26",
    "equity_turnover": 7941.27,
    "derivatives_notional": 1633423.24,
    "options_premium": 7870.34,
    "cash_revenue": 0.5956,
    "options_revenue": 5.1157,
    "futures_revenue": 0.0,
    "total_revenue": 5.7113,
    "has_data": true,
    "source": "live"
  }
}